visual_comparison/__init__.py
visual_comparison/exceptions.py
visual_comparison/utils.py
visual_comparison-1.0.3.dist-info/LICENSE
visual_comparison-1.0.3.dist-info/METADATA
visual_comparison-1.0.3.dist-info/WHEEL
visual_comparison-1.0.3.dist-info/top_level.txt
visual_comparison-1.0.3.dist-info/RECORD
