Metadata-Version: 2.1
Name: visual-comparison
Version: 1.0.3
Summary: Image Comparison Tool
Home-page: https://github.com/BASILAHAMED/visual-comparison
Author: Basil Ahamed
Author-email: sbasil.ahamed@gmail.com
License: MIT
Keywords: visual compare image diff testing
Classifier: Intended Audience :: Developers
Classifier: License :: OSI Approved :: MIT License
Classifier: Operating System :: OS Independent
Classifier: Programming Language :: Python
Classifier: Programming Language :: Python :: 3
Classifier: Programming Language :: Python :: 3.8
Classifier: Programming Language :: Python :: 3.9
Classifier: Programming Language :: Python :: 3.10
License-File: LICENSE
Requires-Dist: numpy ~=1.26.4
Requires-Dist: opencv-python ~=4.9.0.80
Requires-Dist: scikit-image ~=0.23.1
